LICENSE
MANIFEST.in
README.md
setup.py
key_musicz_res/__init__.py
key_musicz_res/__main__.py
key_musicz_res.egg-info/PKG-INFO
key_musicz_res.egg-info/SOURCES.txt
key_musicz_res.egg-info/dependency_links.txt
key_musicz_res.egg-info/requires.txt
key_musicz_res.egg-info/top_level.txt
key_musicz_res/res/piano1_from_TimGM6mb.sf2
key_musicz_res/win_lib/SDL3.dll
key_musicz_res/win_lib/libfluidsynth-3.dll
key_musicz_res/win_lib/libglib-2.0-0.dll
key_musicz_res/win_lib/libgobject-2.0-0.dll
key_musicz_res/win_lib/libgthread-2.0-0.dll
key_musicz_res/win_lib/libinstpatch-2.dll
key_musicz_res/win_lib/libintl-8.dll
key_musicz_res/win_lib/sndfile.dll