Metadata-Version: 2.1
Name: key-musicz-res
Version: 0.1.1
Summary: 键盘弹钢琴，keyboard to play piano
Home-page: https://github.com/buildCodeZ/key_musicz_res
Author: Zzz
Author-email: 1309458652@qq.com
License: MIT License
Keywords: key_musicz_res
Platform: any
License-File: LICENSE
